an/__init__.py
an-0.0.10.dist-info/licenses/LICENSE
an-0.0.10.dist-info/METADATA
an-0.0.10.dist-info/WHEEL
an-0.0.10.dist-info/top_level.txt
an-0.0.10.dist-info/RECORD
