Metadata-Version: 2.4
Name: an
Version: 0.0.10
Summary: Scraping and parsing amazon
Home-page: https://github.com/t-c-w/an
Author: Thor Whalen
License: apache-2.0
Platform: any
License-File: LICENSE
Dynamic: license-file
